swarm/__init__.py
swarm/core/__init__.py
swarm/core/gemini.py
swarm/core/hello.py
ai_swarm-0.1.7.dist-info/METADATA
ai_swarm-0.1.7.dist-info/WHEEL
ai_swarm-0.1.7.dist-info/licenses/LICENSE
ai_swarm-0.1.7.dist-info/RECORD
